llm_samplers/__init__.py
llm_samplers/anti_slop.py
llm_samplers/base.py
llm_samplers/beam.py
llm_samplers/min_p.py
llm_samplers/py.typed
llm_samplers/qalign.py
llm_samplers/temperature.py
llm_samplers/top_k.py
llm_samplers/top_p.py
llm_samplers/xtc.py
llm_samplers-0.1.3.dist-info/licenses/LICENSE
llm_samplers-0.1.3.dist-info/METADATA
llm_samplers-0.1.3.dist-info/WHEEL
llm_samplers-0.1.3.dist-info/top_level.txt
llm_samplers-0.1.3.dist-info/RECORD
