Metadata-Version: 2.4
Name: llm-samplers
Version: 0.1.3
Summary: A library for advanced LLM sampling techniques
Author-email: Ian Timmis <ianmtimmis@gmail.com>
License: MIT
Project-URL: Homepage, https://github.com/iantimmis/llm-samplers
Project-URL: Repository, https://github.com/iantimmis/llm-samplers.git
Project-URL: Documentation, https://llm-samplers.readthedocs.io/
Classifier: Programming Language :: Python :: 3
Classifier: Operating System :: OS Independent
Requires-Python: >=3.9
License-File: LICENSE
Requires-Dist: torch>=2.0.0
Requires-Dist: transformers>=4.30.0
Requires-Dist: numpy>=1.24.0
Dynamic: license-file
